XStatic_Pygments-2.9.0.1-py3.13-nspkg.pth
xstatic/pkg/pygments/__init__.py
xstatic/pkg/pygments/data/css/abap.css
xstatic/pkg/pygments/data/css/algol.css
xstatic/pkg/pygments/data/css/algol_nu.css
xstatic/pkg/pygments/data/css/arduino.css
xstatic/pkg/pygments/data/css/autumn.css
xstatic/pkg/pygments/data/css/borland.css
xstatic/pkg/pygments/data/css/bw.css
xstatic/pkg/pygments/data/css/colorful.css
xstatic/pkg/pygments/data/css/default.css
xstatic/pkg/pygments/data/css/emacs.css
xstatic/pkg/pygments/data/css/friendly.css
xstatic/pkg/pygments/data/css/fruity.css
xstatic/pkg/pygments/data/css/igor.css
xstatic/pkg/pygments/data/css/lovelace.css
xstatic/pkg/pygments/data/css/manni.css
xstatic/pkg/pygments/data/css/monokai.css
xstatic/pkg/pygments/data/css/murphy.css
xstatic/pkg/pygments/data/css/native.css
xstatic/pkg/pygments/data/css/pastie.css
xstatic/pkg/pygments/data/css/perldoc.css
xstatic/pkg/pygments/data/css/rainbow_dash.css
xstatic/pkg/pygments/data/css/rrt.css
xstatic/pkg/pygments/data/css/sas.css
xstatic/pkg/pygments/data/css/stata.css
xstatic/pkg/pygments/data/css/tango.css
xstatic/pkg/pygments/data/css/trac.css
xstatic/pkg/pygments/data/css/vim.css
xstatic/pkg/pygments/data/css/vs.css
xstatic/pkg/pygments/data/css/xcode.css
xstatic_pygments-2.9.0.1.dist-info/METADATA
xstatic_pygments-2.9.0.1.dist-info/WHEEL
xstatic_pygments-2.9.0.1.dist-info/namespace_packages.txt
xstatic_pygments-2.9.0.1.dist-info/top_level.txt
xstatic_pygments-2.9.0.1.dist-info/RECORD
