Metadata-Version: 2.4
Name: XStatic-Pygments
Version: 2.9.0.1
Summary: Pygments 2.9.0 (XStatic packaging standard)
Home-page: https://pygments.org/
Maintainer: Thomas Waldmann
Maintainer-email: tw@waldmann-edv.de
License: (same as Pygments)
Keywords: pygments xstatic
Platform: any
Dynamic: description
Dynamic: home-page
Dynamic: keywords
Dynamic: license
Dynamic: maintainer
Dynamic: maintainer-email
Dynamic: platform
Dynamic: summary
